{"USDC[hts]-USD Coin-HEDERA-USD Coin": {"decimals": 6, "id": "0.0.1055459", "name": "USD Coin", "symbol": "USDC[hts]", "cmc_id": 3408, "token_name": "USD Coin", "type": "HEDERA", "cmc_rank": 6}, "USDT[hts]-Tether USD-HEDERA-Tether USD": {"decimals": 6, "id": "0.0.1055472", "name": "Tether USD", "symbol": "USDT[hts]", "cmc_id": 825, "token_name": "Tether USD", "type": "HEDERA", "cmc_rank": 3}, "DAI[hts]-Dai Stablecoin-HEDERA-Dai Stablecoin": {"decimals": 8, "id": "0.0.1055477", "name": "Dai Stablecoin", "symbol": "DAI[hts]", "cmc_id": 4943, "token_name": "Dai Stablecoin", "type": "HEDERA", "cmc_rank": 15}, "WBTC[hts]-Wrapped BTC-HEDERA-Wrapped BTC": {"decimals": 8, "id": "0.0.1055483", "name": "Wrapped BTC", "symbol": "WBTC[hts]", "cmc_id": 3717, "token_name": "Wrapped BTC", "type": "HEDERA", "cmc_rank": 17}, "LINK[hts]-ChainLink Token-HEDERA-ChainLink Token": {"decimals": 8, "id": "0.0.1055495", "name": "ChainLink Token", "symbol": "LINK[hts]", "cmc_id": 1975, "token_name": "ChainLink Token", "type": "HEDERA", "cmc_rank": 21}, "AAVE[hts]-Aave Token-HEDERA-Aave Token": {"decimals": 8, "id": "0.0.1055498", "name": "Aave Token", "symbol": "AAVE[hts]", "cmc_id": 7278, "token_name": "Aave Token", "type": "HEDERA", "cmc_rank": 44}, "HBAR-WHBAR [old]-HEDERA-WHBAR [old]": {"decimals": 8, "id": "0.0.1062664", "name": "WHBAR [old]", "symbol": "HBAR", "cmc_id": 4642, "token_name": "WHBAR [old]", "type": "HEDERA", "cmc_rank": 30}, "LIL-LIL-HEDERA-LIL": {"decimals": 0, "id": "0.0.1079680", "name": "LIL", "symbol": "LIL", "cmc_id": 11597, "token_name": "LIL", "type": "HEDERA", "cmc_rank": 1000000}, "WHALE-WHALE-HEDERA-WHALE": {"decimals": 2, "id": "0.0.1144501", "name": "WHALE", "symbol": "WHALE", "cmc_id": 6679, "token_name": "WHALE", "type": "HEDERA", "cmc_rank": 908}, "WBNB[hts]-Wrapped BNB[hts]-HEDERA-Wrapped BNB[hts]": {"decimals": 8, "id": "0.0.1157005", "name": "Wrapped BNB[hts]", "symbol": "WBNB[hts]", "cmc_id": 7192, "token_name": "Wrapped BNB[hts]", "type": "HEDERA", "cmc_rank": 214}, "WAVAX[hts]-Wrapped AVAX[hts]-HEDERA-Wrapped AVAX[hts]": {"decimals": 8, "id": "0.0.1157020", "name": "Wrapped AVAX[hts]", "symbol": "WAVAX[hts]", "cmc_id": 9462, "token_name": "Wrapped AVAX[hts]", "type": "HEDERA", "cmc_rank": 2154}, "GRELF-GRELF-HEDERA-GRELF": {"decimals": 8, "id": "0.0.1159074", "name": "GRELF", "symbol": "GRELF", "cmc_id": 24191, "token_name": "GRELF", "type": "HEDERA", "cmc_rank": 4980}, "SOF-SOF-HEDERA-SOF": {"decimals": 7, "id": "0.0.1237128", "name": "SOF", "symbol": "SOF", "cmc_id": 15950, "token_name": "SOF", "type": "HEDERA", "cmc_rank": 1000000}, "JAM-JAM-HEDERA-JAM": {"decimals": 8, "id": "0.0.127877", "name": "JAM", "symbol": "JAM", "cmc_id": 11420, "token_name": "JAM", "type": "HEDERA", "cmc_rank": 3079}, "JOE[hts]-JOE-HEDERA-JOE": {"decimals": 8, "id": "0.0.1302480", "name": "JOE", "symbol": "JOE[hts]", "cmc_id": 11396, "token_name": "JOE", "type": "HEDERA", "cmc_rank": 200}, "GMX[hts]-GMX-HEDERA-GMX": {"decimals": 8, "id": "0.0.1302499", "name": "GMX", "symbol": "GMX[hts]", "cmc_id": 11857, "token_name": "GMX", "type": "HEDERA", "cmc_rank": 91}, "PTP[hts]-Platypus Finance-HEDERA-Platypus Finance": {"decimals": 8, "id": "0.0.1302509", "name": "Platypus Finance", "symbol": "PTP[hts]", "cmc_id": 16231, "token_name": "Platypus Finance", "type": "HEDERA", "cmc_rank": 1451}, "QI[hts]-BENQI-HEDERA-BENQI": {"decimals": 8, "id": "0.0.1302512", "name": "BENQI", "symbol": "QI[hts]", "cmc_id": 9288, "token_name": "BENQI", "type": "HEDERA", "cmc_rank": 541}, "CAKE[hts]-PancakeSwap-HEDERA-PancakeSwap": {"decimals": 8, "id": "0.0.1302527", "name": "PancakeSwap", "symbol": "CAKE[hts]", "cmc_id": 7186, "token_name": "PancakeSwap", "type": "HEDERA", "cmc_rank": 101}, "BUSD[hts]-Binance USD-HEDERA-Binance USD": {"decimals": 8, "id": "0.0.1302528", "name": "Binance USD", "symbol": "BUSD[hts]", "cmc_id": 4687, "token_name": "Binance USD", "type": "HEDERA", "cmc_rank": 23}, "COMP[hts]-Compound-HEDERA-Compound": {"decimals": 8, "id": "0.0.1304729", "name": "Compound", "symbol": "COMP[hts]", "cmc_id": 5692, "token_name": "Compound", "type": "HEDERA", "cmc_rank": 89}, "SHIB[hts]-Shiba Inu-HEDERA-Shiba Inu": {"decimals": 8, "id": "0.0.1304735", "name": "Shiba Inu", "symbol": "SHIB[hts]", "cmc_id": 5994, "token_name": "Shiba Inu", "type": "HEDERA", "cmc_rank": 12}, "APE[hts]-ApeCoin-HEDERA-ApeCoin": {"decimals": 8, "id": "0.0.1304748", "name": "ApeCoin", "symbol": "APE[hts]", "cmc_id": 18876, "token_name": "ApeCoin", "type": "HEDERA", "cmc_rank": 56}, "QNT[hts]-Quant-HEDERA-Quant": {"decimals": 8, "id": "0.0.1304757", "name": "Quant", "symbol": "QNT[hts]", "cmc_id": 3155, "token_name": "Quant", "type": "HEDERA", "cmc_rank": 39}, "AXS[hts]-Axie Infinity-HEDERA-Axie Infinity": {"decimals": 8, "id": "0.0.1304767", "name": "Axie Infinity", "symbol": "AXS[hts]", "cmc_id": 6783, "token_name": "Axie Infinity", "type": "HEDERA", "cmc_rank": 47}, "LCX[hts]-LCX-HEDERA-LCX": {"decimals": 8, "id": "0.0.1304772", "name": "LCX", "symbol": "LCX[hts]", "cmc_id": 4950, "token_name": "LCX", "type": "HEDERA", "cmc_rank": 440}, "CRV[hts]-Curve DAO-HEDERA-Curve DAO": {"decimals": 8, "id": "0.0.1304781", "name": "Curve DAO", "symbol": "CRV[hts]", "cmc_id": 6538, "token_name": "Curve DAO", "type": "HEDERA", "cmc_rank": 74}, "TUSD[hts]-TrueUSD-HEDERA-TrueUSD": {"decimals": 8, "id": "0.0.1304788", "name": "TrueUSD", "symbol": "TUSD[hts]", "cmc_id": 2563, "token_name": "TrueUSD", "type": "HEDERA", "cmc_rank": 26}, "rUSD-rUSD-HEDERA-rUSD": {"decimals": 6, "id": "0.0.1320271", "name": "rUSD", "symbol": "rUSD", "cmc_id": 18303, "token_name": "rUSD", "type": "HEDERA", "cmc_rank": 1000000}, "HBAR-WHBAR [new]-HEDERA-WHBAR [new]": {"decimals": 8, "id": "0.0.1456986", "name": "WHBAR [new]", "symbol": "HBAR", "cmc_id": 4642, "token_name": "WHBAR [new]", "type": "HEDERA", "cmc_rank": 30}, "XSAUCE-xSAUCE-HEDERA-xSAUCE": {"decimals": 6, "id": "0.0.1460200", "name": "xSAUCE", "symbol": "XSAUCE", "cmc_id": 23069, "token_name": "xSAUCE", "type": "HEDERA", "cmc_rank": 4415}, "SD[hts]-Stader-HEDERA-Stader": {"decimals": 8, "id": "0.0.1463375", "name": "Stader", "symbol": "SD[hts]", "cmc_id": 12623, "token_name": "Stader", "type": "HEDERA", "cmc_rank": 558}, "HEX-Hashgraph Exchange-HEDERA-Hashgraph Exchange": {"decimals": 5, "id": "0.0.148698", "name": "Hashgraph Exchange", "symbol": "HEX", "cmc_id": 5015, "token_name": "Hashgraph Exchange", "type": "HEDERA", "cmc_rank": 209}, "PBAR-PBAR-HEDERA-PBAR": {"decimals": 8, "id": "0.0.1738930", "name": "PBAR", "symbol": "PBAR", "cmc_id": 26203, "token_name": "PBAR", "type": "HEDERA", "cmc_rank": 6837}, "HELI-HeliSwap-HEDERA-HeliSwap": {"decimals": 8, "id": "0.0.1937609", "name": "HeliSwap", "symbol": "HELI", "cmc_id": 23643, "token_name": "HeliSwap", "type": "HEDERA", "cmc_rank": 1000000}, "ASSET-iAssets-HEDERA-iAssets": {"decimals": 6, "id": "0.0.1991880", "name": "iAssets", "symbol": "ASSET", "cmc_id": 20344, "token_name": "iAssets", "type": "HEDERA", "cmc_rank": 3830}, "SIKI-Siki-HEDERA-Siki": {"decimals": 8, "id": "0.0.209368", "name": "Siki", "symbol": "SIKI", "cmc_id": 12968, "token_name": "Siki", "type": "HEDERA", "cmc_rank": 1000000}, "DINU-D\u00c4NKINU-HEDERA-D\u00c4NKINU": {"decimals": 3, "id": "0.0.2122292", "name": "D\u00c4NKINU", "symbol": "DINU", "cmc_id": 21551, "token_name": "D\u00c4NKINU", "type": "HEDERA", "cmc_rank": 7166}, "GOAT-GOAT-HEDERA-GOAT": {"decimals": 4, "id": "0.0.2137254", "name": "GOAT", "symbol": "GOAT", "cmc_id": 9069, "token_name": "GOAT", "type": "HEDERA", "cmc_rank": 6957}, "CHAIN-Chain Token-HEDERA-Chain Token": {"decimals": 2, "id": "0.0.2160169", "name": "Chain Token", "symbol": "CHAIN", "cmc_id": 6744, "token_name": "Chain Token", "type": "HEDERA", "cmc_rank": 3950}, "KARATE-Karate-HEDERA-Karate": {"decimals": 8, "id": "0.0.2283230", "name": "Karate", "symbol": "KARATE", "cmc_id": 25224, "token_name": "Karate", "type": "HEDERA", "cmc_rank": 2870}, "INARI-Inari Gold-HEDERA-Inari Gold": {"decimals": 8, "id": "0.0.2303594", "name": "Inari Gold", "symbol": "INARI", "cmc_id": 10809, "token_name": "Inari Gold", "type": "HEDERA", "cmc_rank": 1000000}, "LOT-Lotto-HEDERA-Lotto": {"decimals": 0, "id": "0.0.2964083", "name": "Lotto", "symbol": "LOT", "cmc_id": 82, "token_name": "Lotto", "type": "HEDERA", "cmc_rank": 1000000}, "GC-GCoin-HEDERA-GCoin": {"decimals": 6, "id": "0.0.3241481", "name": "GCoin", "symbol": "GC", "cmc_id": 26960, "token_name": "GCoin", "type": "HEDERA", "cmc_rank": 3159}, "USDC-USD Coin-HEDERA-USD Coin": {"decimals": 6, "id": "0.0.456858", "name": "USD Coin", "symbol": "USDC", "cmc_id": 3408, "token_name": "USD Coin", "type": "HEDERA", "cmc_rank": 6}, "WMATIC[hts]-Wrapped Matic[hts]-HEDERA-Wrapped Matic[hts]": {"decimals": 8, "id": "0.0.540318", "name": "Wrapped Matic[hts]", "symbol": "WMATIC[hts]", "cmc_id": 8925, "token_name": "Wrapped Matic[hts]", "type": "HEDERA", "cmc_rank": 2139}, "WETH[hts]-Wrapped Ether[hts]-HEDERA-Wrapped Ether[hts]": {"decimals": 8, "id": "0.0.541564", "name": "Wrapped Ether[hts]", "symbol": "WETH[hts]", "cmc_id": 2396, "token_name": "Wrapped Ether[hts]", "type": "HEDERA", "cmc_rank": 2135}, "DOV[hts]-DOVU-HEDERA-DOVU": {"decimals": 8, "id": "0.0.3716059", "name": "DOVU", "symbol": "DOV[hts]", "cmc_id": 2110, "token_name": "DOVU", "type": "HEDERA", "cmc_rank": 1043}, "NADA-NaDa Protocol Token-HEDERA-NaDa Protocol Token": {"decimals": 6, "id": "0.0.629591", "name": "NaDa Protocol Token", "symbol": "NADA", "cmc_id": 21672, "token_name": "NaDa Protocol Token", "type": "HEDERA", "cmc_rank": 2205}, "SAUCE-SAUCE-HEDERA-SAUCE": {"decimals": 6, "id": "0.0.731861", "name": "SAUCE", "symbol": "SAUCE", "cmc_id": 21914, "token_name": "SAUCE", "type": "HEDERA", "cmc_rank": 2543}, "ETT-Energy Trade Token-HEDERA-Energy Trade Token": {"decimals": 0, "id": "0.0.784681", "name": "Energy Trade Token", "symbol": "ETT", "cmc_id": 6429, "token_name": "Energy Trade Token", "type": "HEDERA", "cmc_rank": 1000000}, "HSUITE-HbarSuite-HEDERA-HbarSuite": {"decimals": 4, "id": "0.0.786931", "name": "HbarSuite", "symbol": "HSUITE", "cmc_id": 24790, "token_name": "HbarSuite", "type": "HEDERA", "cmc_rank": 4387}, "HBARX-HBARX-HEDERA-HBARX": {"decimals": 8, "id": "0.0.834116", "name": "HBARX", "symbol": "HBARX", "cmc_id": 23185, "token_name": "HBARX", "type": "HEDERA", "cmc_rank": 2923}, "CLXY-Calaxy Tokens-HEDERA-Calaxy Tokens": {"decimals": 6, "id": "0.0.859814", "name": "Calaxy Tokens", "symbol": "CLXY", "cmc_id": 19841, "token_name": "Calaxy Tokens", "type": "HEDERA", "cmc_rank": 1000000}, "CREAM-CREAM-HEDERA-CREAM": {"decimals": 0, "id": "0.0.926385", "name": "CREAM", "symbol": "CREAM", "cmc_id": 27058, "token_name": "CREAM", "type": "HEDERA", "cmc_rank": 1000000}, "HST-HeadStarter-HEDERA-HeadStarter": {"decimals": 8, "id": "0.0.968069", "name": "HeadStarter", "symbol": "HST", "cmc_id": 21019, "token_name": "HeadStarter", "type": "HEDERA", "cmc_rank": 5058}}